pyMetaheuristic/__init__.py
pyMetaheuristic/algorithm/__init__.py
pyMetaheuristic/algorithm/abco.py
pyMetaheuristic/algorithm/acgwo.py
pyMetaheuristic/algorithm/afsa.py
pyMetaheuristic/algorithm/alo.py
pyMetaheuristic/algorithm/aoa.py
pyMetaheuristic/algorithm/ars.py
pyMetaheuristic/algorithm/bat_a.py
pyMetaheuristic/algorithm/bbo.py
pyMetaheuristic/algorithm/ca.py
pyMetaheuristic/algorithm/cat_so.py
pyMetaheuristic/algorithm/cem.py
pyMetaheuristic/algorithm/chicken_so.py
pyMetaheuristic/algorithm/clonalg.py
pyMetaheuristic/algorithm/coati_oa.py
pyMetaheuristic/algorithm/cockroach_so.py
pyMetaheuristic/algorithm/csa.py
pyMetaheuristic/algorithm/cuckoo_s.py
pyMetaheuristic/algorithm/da.py
pyMetaheuristic/algorithm/de.py
pyMetaheuristic/algorithm/dfo.py
pyMetaheuristic/algorithm/dvba.py
pyMetaheuristic/algorithm/eho.py
pyMetaheuristic/algorithm/fda.py
pyMetaheuristic/algorithm/firefly_a.py
pyMetaheuristic/algorithm/fpa.py
pyMetaheuristic/algorithm/ga.py
pyMetaheuristic/algorithm/gmo.py
pyMetaheuristic/algorithm/goa.py
pyMetaheuristic/algorithm/gsa.py
pyMetaheuristic/algorithm/gwo.py
pyMetaheuristic/algorithm/hho.py
pyMetaheuristic/algorithm/hsa.py
pyMetaheuristic/algorithm/hus.py
pyMetaheuristic/algorithm/i_gwo.py
pyMetaheuristic/algorithm/i_woa.py
pyMetaheuristic/algorithm/jso.py
pyMetaheuristic/algorithm/jy.py
pyMetaheuristic/algorithm/kha.py
pyMetaheuristic/algorithm/mbo.py
pyMetaheuristic/algorithm/memetic_a.py
pyMetaheuristic/algorithm/mfa.py
pyMetaheuristic/algorithm/mvo.py
pyMetaheuristic/algorithm/pbil.py
pyMetaheuristic/algorithm/pfa.py
pyMetaheuristic/algorithm/pso.py
pyMetaheuristic/algorithm/random_s.py
pyMetaheuristic/algorithm/sa.py
pyMetaheuristic/algorithm/sine_cosine_a.py
pyMetaheuristic/algorithm/sos.py
pyMetaheuristic/algorithm/spbo.py
pyMetaheuristic/algorithm/ssa.py
pyMetaheuristic/algorithm/tlbo.py
pyMetaheuristic/algorithm/woa.py
pyMetaheuristic/test_function/__init__.py
pyMetaheuristic/test_function/single.py
pyMetaheuristic/utils/__init__.py
pyMetaheuristic-1.9.5.dist-info/LICENSE
pyMetaheuristic-1.9.5.dist-info/METADATA
pyMetaheuristic-1.9.5.dist-info/WHEEL
pyMetaheuristic-1.9.5.dist-info/top_level.txt
pyMetaheuristic-1.9.5.dist-info/RECORD
