Metadata-Version: 2.1
Name: pyMetaheuristic
Version: 1.9.5
Summary: pyMetaheuristic: A Comprehensive Python Library for Optimization
Home-page: https://github.com/Valdecy/pyMetaheuristic
Author: Valdecy Pereira
Author-email: valdecy.pereira@gmail.com
License: GNU
License-File: LICENSE
Requires-Dist: numpy
Requires-Dist: plotly
Requires-Dist: scipy
